setup.py
miniatureOctoBatman/__init__.py
miniatureOctoBatman/cjdns.py
miniatureOctoBatman/mifi.py
miniatureOctoBatman/packages.py
miniatureOctoBatman/web.py
miniatureOctoBatman.egg-info/PKG-INFO
miniatureOctoBatman.egg-info/SOURCES.txt
miniatureOctoBatman.egg-info/dependency_links.txt
miniatureOctoBatman.egg-info/namespace_packages.txt
miniatureOctoBatman.egg-info/top_level.txt