Metadata-Version: 1.0
Name: miniatureOctoBatman
Version: 0.1.2
Summary: Finn's collection of powerline modules
Home-page: https://github.com/thefinn93/miniature-octo-batman
Author: Finn Herzfeld
Author-email: finn@finn.io
License: UNKNOWN
Platform: UNKNOWN
